{
  "albums": [
    {
      "title": "misty mt.macedon",
      "album_number": 3,
      "album_id": "3e287acc-274c-4cf5-906c-93e1d6a2d204",
      "folder_name": "mt.macedon",
      "date": "2018-01-22",
      "cover_image": "1.jpg",
      "subtitle": ""
    },
    {
      "title": "derelict",
      "album_number": 4,
      "album_id": "2399b40a-864c-4227-9be1-5a5b77026072",
      "folder_name": "derelict",
      "date": "2018-01-09",
      "cover_image": "1.jpg",
      "subtitle": ""
    },
    {
      "title": "furred friends",
      "album_number": 5,
      "album_id": "a9927b18-436b-44ed-b02a-c814a459f37d",
      "folder_name": "furred-friends",
      "date": "2018-01-09",
      "cover_image": "poohie.jpg",
      "subtitle": ""
    },
    {
      "title": "a wicked bushland",
      "album_number": 6,
      "album_id": "591ad329-dd4e-4940-9119-288118cb6547",
      "folder_name": "bushland",
      "date": "2018-01-09",
      "cover_image": "1.jpg",
      "subtitle": ""
    }
  ]
}